{
  "emoji_char": "\ud83e\uddb4",
  "emoji_code": "U+1F9B4",
  "layers": [
    {
      "layer_index": 0,
      "glyph_name": "glyph10605",
      "color": {
        "r": 0,
        "g": 0,
        "b": 0
      },
      "hex": "#000000",
      "svg_file": "emoji_layer_00.svg"
    },
    {
      "layer_index": 1,
      "glyph_name": "glyph10606",
      "color": {
        "r": 242,
        "g": 242,
        "b": 242
      },
      "hex": "#f2f2f2",
      "svg_file": "emoji_layer_01.svg"
    },
    {
      "layer_index": 2,
      "glyph_name": "glyph10607",
      "color": {
        "r": 166,
        "g": 166,
        "b": 166
      },
      "hex": "#a6a6a6",
      "svg_file": "emoji_layer_02.svg"
    }
  ]
}