[
  {
    "char": "🌆",
    "x": 239,
    "y": 268.5,
    "size": 422,
    "rotation": 0,
    "rotationSwing": 0,
    "animationHandle": null,
    "isSwinging": false,
    "isRotating": false,
    "isScaling": false,
    "isMoving": false
  },
  {
    "char": "🛸",
    "x": 71,
    "y": 270.5,
    "size": 116,
    "rotation": 0,
    "rotationSwing": 0,
    "animationHandle": null,
    "isSwinging": false,
    "isRotating": false,
    "isScaling": false,
    "isMoving": false
  },
  {
    "char": "🌃",
    "x": 299,
    "y": 308.5,
    "size": 278,
    "rotation": 0,
    "rotationSwing": 0,
    "animationHandle": null,
    "isFlipped": true,
    "isSwinging": false,
    "isRotating": false,
    "isScaling": false,
    "isMoving": false
  },
  {
    "char": "🎡",
    "x": 424.5,
    "y": 321.5,
    "size": 303,
    "rotation": 0,
    "rotationSwing": 0,
    "animationHandle": null,
    "isSwinging": false,
    "isRotating": false,
    "isScaling": false,
    "isMoving": false
  }
]